{
  "name": "Alexa Grasso",
  "profile_url": "https://ufc.com/images/styles/athlete_bio_full_body/s3/2025-05/GRASSO_ALEXA_L_05-10.png?itok=vx3rIdSg",
  "weight_class": "Women's Flyweight",
  "record": {
    "wins": "16",
    "losses": "5",
    "draws": "1"
  },
  "win_methods": {
    "KO": "25",
    "DEC": "63",
    "SUB": "13"
  },
  "bio": {
    "age": "32",
    "height": "65.00",
    "reach": "66.00",
    "leg_reach": "37.50",
    "fighting_style": "MMA"
  },
  "fight_stats": {
    "SLpM": "4.11",
    "SApM": "3.73",
    "TDAvg": "0.41",
    "Sub.Avg": "0.61",
    "Str.Def": "58",
    "TDDef": "55",
    "KDAvg": "0.07",
    "Avg Fight Time": "15:48",
    "Str. Acc.": "41",
    "TD Acc.": "35"
  }
}