{
  "name": "Alexis Dufresne",
  "profile_url": "https://ufc.com/images/styles/athlete_bio_full_body/s3/2021-08/Alexis-Dufresne_479266_LeftFullBodyImage.png?itok=uUPH-igl",
  "weight_class": "Women's Bantamweight",
  "record": {
    "wins": "5",
    "losses": "2",
    "draws": "0"
  },
  "win_methods": {
    "KO": "60",
    "DEC": "0",
    "SUB": "40"
  },
  "bio": {
    "age": "N/A",
    "height": "69.00",
    "reach": "68.00",
    "leg_reach": "N/A",
    "fighting_style": "N/A"
  },
  "fight_stats": {
    "SLpM": "1.33",
    "SApM": "3.33",
    "TDAvg": "1.50",
    "Sub.Avg": "0.00",
    "Str.Def": "61",
    "TDDef": "50",
    "KDAvg": "0.00",
    "Avg Fight Time": "15:00",
    "Str. Acc.": "28",
    "TD Acc.": "50"
  }
}