{
  "name": "Anderson Silva",
  "profile_url": "https://ufc.com/images/styles/athlete_bio_full_body/s3/image/fighter_images/Anderson_Silva/SILVA_ANDERSON_L.png?VersionId=oqn6CIQraQL7H1Maglm56oOzYSKBL0n0&itok=lPUguW3f",
  "weight_class": "Middleweight",
  "record": {
    "wins": "34",
    "losses": "11",
    "draws": "0"
  },
  "win_methods": {
    "KO": "65",
    "DEC": "24",
    "SUB": "12"
  },
  "bio": {
    "age": "48",
    "height": "74.00",
    "reach": "77.00",
    "leg_reach": "42.50",
    "fighting_style": "N/A"
  },
  "fight_stats": {
    "SLpM": "3.05",
    "SApM": "2.05",
    "TDAvg": "0.50",
    "Sub.Avg": "0.79",
    "Str.Def": "61",
    "TDDef": "69",
    "KDAvg": "0.86",
    "Avg Fight Time": "10:15",
    "Str. Acc.": "62",
    "TD Acc.": "78"
  }
}