{
  "name": "Brady Huang",
  "profile_url": "https://ufc.com/images/styles/athlete_bio_full_body/s3/2022-03/4b912d26-611a-4ad6-a08a-26f7afdeb1ee%252FHUANG_BRADY_R_CS.png?itok=BiPLTNhy",
  "weight_class": "Bantamweight",
  "record": {
    "wins": "11",
    "losses": "2",
    "draws": "0"
  },
  "win_methods": {
    "KO": "0",
    "DEC": "0",
    "SUB": "0"
  },
  "bio": {
    "age": "30",
    "height": "N/A",
    "reach": "N/A",
    "leg_reach": "N/A",
    "fighting_style": "N/A"
  },
  "fight_stats": {
    "SLpM": "4.62",
    "SApM": "10.77",
    "TDAvg": "0.00",
    "Sub.Avg": "0.00",
    "Str.Def": "30",
    "TDDef": "0.00",
    "KDAvg": "00:39",
    "Avg Fight Time": "N/A",
    "Str. Acc.": "38",
    "TD Acc.": "0"
  }
}