{
  "name": "Charles Byrd",
  "profile_url": "https://ufc.com/images/styles/athlete_bio_full_body/s3/image/ufc-fighter-container/67587/profile-galery/fullbodyleft-picture/BYRD_CHARLES_L.png?VersionId=qAx8l64VSdMJuGwxGJa0rGCRfL2Dek0D&itok=OsB-3FsF",
  "weight_class": "Middleweight",
  "record": {
    "wins": "10",
    "losses": "7",
    "draws": "0"
  },
  "win_methods": {
    "KO": "30",
    "DEC": "20",
    "SUB": "50"
  },
  "bio": {
    "age": "39",
    "height": "70.00",
    "reach": "73.00",
    "leg_reach": "39.00",
    "fighting_style": "N/A"
  },
  "fight_stats": {
    "SLpM": "3.43",
    "SApM": "2.63",
    "TDAvg": "2.50",
    "Sub.Avg": "1.50",
    "Str.Def": "56",
    "TDDef": "40",
    "KDAvg": "0.00",
    "Avg Fight Time": "05:00",
    "Str. Acc.": "56",
    "TD Acc.": "50"
  }
}