{
  "name": "Dakota Bush",
  "profile_url": "https://ufc.com/images/styles/athlete_bio_full_body/s3/2021-06/BUSH_DAKOTA_L_04-17.png?itok=PoogE25R",
  "weight_class": "Lightweight",
  "record": {
    "wins": "8",
    "losses": "4",
    "draws": "0"
  },
  "win_methods": {
    "KO": "25",
    "DEC": "25",
    "SUB": "50"
  },
  "bio": {
    "age": "29",
    "height": "70.00",
    "reach": "73.50",
    "leg_reach": "39.00",
    "fighting_style": "Freestyle"
  },
  "fight_stats": {
    "SLpM": "2.77",
    "SApM": "4.42",
    "TDAvg": "2.40",
    "Sub.Avg": "0.00",
    "Str.Def": "42",
    "TDDef": "0.00",
    "KDAvg": "09:24",
    "Avg Fight Time": "N/A",
    "Str. Acc.": "39",
    "TD Acc.": "33"
  }
}