{
  "name": "Danny Martinez",
  "profile_url": "https://ufc.com/images/styles/athlete_bio_full_body/s3/2022-03/248f05a2-c213-4f71-9561-e9cba27c8d16%252FDanny-Martinez_453465_LeftFullBodyImage.png?itok=qYEfrHGd",
  "weight_class": "Flyweight",
  "record": {
    "wins": "18",
    "losses": "7",
    "draws": "0"
  },
  "win_methods": {
    "KO": "44",
    "DEC": "33",
    "SUB": "22"
  },
  "bio": {
    "age": "38",
    "height": "65.00",
    "reach": "N/A",
    "leg_reach": "N/A",
    "fighting_style": "N/A"
  },
  "fight_stats": {
    "SLpM": "2.73",
    "SApM": "3.77",
    "TDAvg": "3.00",
    "Sub.Avg": "0.00",
    "Str.Def": "64",
    "TDDef": "37",
    "KDAvg": "0.20",
    "Avg Fight Time": "15:00",
    "Str. Acc.": "29",
    "TD Acc.": "45"
  }
}