{
  "name": "JJ Aldrich",
  "profile_url": "https://ufc.com/images/styles/athlete_bio_full_body/s3/2025-02/ALDRICH_JJ_L_05-11.png?itok=btLZsbxb",
  "weight_class": "Women's Flyweight",
  "record": {
    "wins": "14",
    "losses": "7",
    "draws": "0"
  },
  "win_methods": {
    "KO": "21",
    "DEC": "79",
    "SUB": "0"
  },
  "bio": {
    "age": "32",
    "height": "65.00",
    "reach": "67.50",
    "leg_reach": "37.00",
    "fighting_style": "Striker"
  },
  "fight_stats": {
    "SLpM": "3.96",
    "SApM": "4.32",
    "TDAvg": "0.75",
    "Sub.Avg": "0.00",
    "Str.Def": "61",
    "TDDef": "68",
    "KDAvg": "0.00",
    "Avg Fight Time": "13:47",
    "Str. Acc.": "47",
    "TD Acc.": "27"
  }
}