{
  "name": "Josh Clopton",
  "profile_url": null,
  "weight_class": "Featherweight",
  "record": {
    "wins": "6",
    "losses": "2",
    "draws": "1"
  },
  "win_methods": {
    "KO": "0",
    "DEC": "0",
    "SUB": "0"
  },
  "bio": {
    "age": "41",
    "height": "66.00",
    "reach": "68.00",
    "leg_reach": "N/A",
    "fighting_style": "N/A"
  },
  "fight_stats": {
    "SLpM": "1.60",
    "SApM": "2.87",
    "TDAvg": "2.00",
    "Sub.Avg": "0.00",
    "Str.Def": "50",
    "TDDef": "75",
    "KDAvg": "0.00",
    "Avg Fight Time": "15:00",
    "Str. Acc.": "64",
    "TD Acc.": "67"
  }
}