{
  "name": "Julia Avila",
  "profile_url": "https://ufc.com/images/styles/athlete_bio_full_body/s3/2025-02/AVILA_JULIA_L_02-15.png?itok=GS2GxUDh",
  "weight_class": "Women's Bantamweight",
  "record": {
    "wins": "9",
    "losses": "4",
    "draws": "0"
  },
  "win_methods": {
    "KO": "44",
    "DEC": "33",
    "SUB": "22"
  },
  "bio": {
    "age": "36",
    "height": "67.00",
    "reach": "68.00",
    "leg_reach": "38.00",
    "fighting_style": "N/A"
  },
  "fight_stats": {
    "SLpM": "2.81",
    "SApM": "3.28",
    "TDAvg": "0.63",
    "Sub.Avg": "0.21",
    "Str.Def": "56",
    "TDDef": "53",
    "KDAvg": "0.21",
    "Avg Fight Time": "11:49",
    "Str. Acc.": "42",
    "TD Acc.": "38"
  }
}