{
  "name": "Justin Willis",
  "profile_url": "https://ufc.com/images/styles/athlete_bio_full_body/s3/image/ufc-fighter-container/68427/profile-galery/fullbodyleft-picture/WILLIS_JUSTIN_L.png?itok=tOuc7KBu",
  "weight_class": "Heavyweight",
  "record": {
    "wins": "8",
    "losses": "2",
    "draws": "0"
  },
  "win_methods": {
    "KO": "50",
    "DEC": "13",
    "SUB": "38"
  },
  "bio": {
    "age": "35",
    "height": "73.00",
    "reach": "78.00",
    "leg_reach": "41.00",
    "fighting_style": "N/A"
  },
  "fight_stats": {
    "SLpM": "3.37",
    "SApM": "2.57",
    "TDAvg": "0.96",
    "Sub.Avg": "0.00",
    "Str.Def": "58",
    "TDDef": "36",
    "KDAvg": "0.48",
    "Avg Fight Time": "12:31",
    "Str. Acc.": "59",
    "TD Acc.": "67"
  }
}