{
  "name": "Matt Hughes",
  "profile_url": null,
  "weight_class": "Welterweight",
  "record": {
    "wins": "46",
    "losses": "9",
    "draws": "0"
  },
  "win_methods": {
    "KO": "0",
    "DEC": "0",
    "SUB": "0"
  },
  "bio": {
    "age": "49",
    "height": "69.00",
    "reach": "N/A",
    "leg_reach": "N/A",
    "fighting_style": "N/A"
  },
  "fight_stats": {
    "SLpM": "2.14",
    "SApM": "1.36",
    "TDAvg": "2.95",
    "Sub.Avg": "1.18",
    "Str.Def": "54",
    "TDDef": "35",
    "KDAvg": "0.22",
    "Avg Fight Time": "08:51",
    "Str. Acc.": "53",
    "TD Acc.": "50"
  }
}