{
  "name": "Pedro Falcao",
  "profile_url": "https://ufc.com/images/styles/athlete_bio_full_body/s3/2024-04/FALCAO_PEDRO_L_04-06.png?itok=PROZrX9H",
  "weight_class": "Bantamweight",
  "record": {
    "wins": "16",
    "losses": "5",
    "draws": "0"
  },
  "win_methods": {
    "KO": "38",
    "DEC": "31",
    "SUB": "31"
  },
  "bio": {
    "age": "32",
    "height": "66.00",
    "reach": "66.00",
    "leg_reach": "38.00",
    "fighting_style": "MMA"
  },
  "fight_stats": {
    "SLpM": "3.21",
    "SApM": "3.39",
    "TDAvg": "2.73",
    "Sub.Avg": "0.00",
    "Str.Def": "50",
    "TDDef": "67",
    "KDAvg": "0.00",
    "Avg Fight Time": "14:38",
    "Str. Acc.": "48",
    "TD Acc.": "26"
  }
}