{
  "name": "Rafa Garcia",
  "profile_url": "https://ufc.com/images/styles/athlete_bio_full_body/s3/2025-09/GARCIA_RAFA_L_09-13.png?itok=VVRIbE4K",
  "weight_class": "Lightweight",
  "record": {
    "wins": "18",
    "losses": "4",
    "draws": "0"
  },
  "win_methods": {
    "KO": "6",
    "DEC": "41",
    "SUB": "53"
  },
  "bio": {
    "age": "31",
    "height": "67.00",
    "reach": "70.00",
    "leg_reach": "37.00",
    "fighting_style": "Boxer"
  },
  "fight_stats": {
    "SLpM": "4.01",
    "SApM": "4.47",
    "TDAvg": "3.21",
    "Sub.Avg": "0.25",
    "Str.Def": "61",
    "TDDef": "77",
    "KDAvg": "0.00",
    "Avg Fight Time": "13:30",
    "Str. Acc.": "44",
    "TD Acc.": "43"
  }
}