{
  "name": "Robert Drysdale",
  "profile_url": "https://ufc.com/images/styles/athlete_bio_full_body/s3/2022-03/1028d3fb-7786-469b-ac3c-d0a8fd86a1eb%252Frobert-drysdale_336580_LeftFullBodyImage.png?itok=9cgHhqne",
  "weight_class": "Light Heavyweight",
  "record": {
    "wins": "7",
    "losses": "0",
    "draws": "0"
  },
  "win_methods": {
    "KO": "0",
    "DEC": "0",
    "SUB": "100"
  },
  "bio": {
    "age": "41",
    "height": "75.00",
    "reach": "N/A",
    "leg_reach": "N/A",
    "fighting_style": "N/A"
  },
  "fight_stats": {
    "SLpM": "0.00",
    "SApM": "0.00",
    "TDAvg": "7.32",
    "Sub.Avg": "21.95",
    "Str.Def": "0.00",
    "TDDef": "02:03",
    "KDAvg": "N/A",
    "Avg Fight Time": "N/A",
    "Str. Acc.": "0",
    "TD Acc.": "100"
  }
}