{
  "name": "Zarah Fairn",
  "profile_url": "https://ufc.com/images/styles/athlete_bio_full_body/s3/2023-06/FAIRN_ZARAH_L%296_23.png?itok=-KrjUt5h",
  "weight_class": "Women's Bantamweight",
  "record": {
    "wins": "6",
    "losses": "5",
    "draws": "0"
  },
  "win_methods": {
    "KO": "67",
    "DEC": "33",
    "SUB": "0"
  },
  "bio": {
    "age": "39",
    "height": "68.00",
    "reach": "72.00",
    "leg_reach": "42.00",
    "fighting_style": "MMA"
  },
  "fight_stats": {
    "SLpM": "4.55",
    "SApM": "7.40",
    "TDAvg": "0.00",
    "Sub.Avg": "0.00",
    "Str.Def": "46",
    "TDDef": "60",
    "KDAvg": "0.00",
    "Avg Fight Time": "09:24",
    "Str. Acc.": "31",
    "TD Acc.": "0"
  }
}